[
  {
    "username": "masakoisogai",
    "display_name": "Mama",
    "source": "SBI証券",
    "snapshot_at": "2026-05-01T16:01:02.666570",
    "valuation": 106902213,
    "profit_loss": 32878415,
    "profit_loss_rate": 44.41,
    "acquisition_cost": 74023798
  },
  {
    "username": "masakoisogai",
    "display_name": "Mama",
    "source": "住信SBIネット銀行",
    "snapshot_at": "2026-05-01T16:07:42.712688",
    "valuation": 30033,
    "profit_loss": null,
    "profit_loss_rate": null,
    "acquisition_cost": null
  },
  {
    "username": "nanaisogai",
    "display_name": "Sister",
    "source": "SBI証券",
    "snapshot_at": "2026-05-01T16:02:25.264030",
    "valuation": 12437061,
    "profit_loss": 4390145,
    "profit_loss_rate": 54.55,
    "acquisition_cost": 8046916
  },
  {
    "username": "nanaisogai",
    "display_name": "Sister",
    "source": "三菱UFJ銀行",
    "snapshot_at": "2026-05-01T16:03:22.369340",
    "valuation": 1148058,
    "profit_loss": null,
    "profit_loss_rate": null,
    "acquisition_cost": null
  },
  {
    "username": "yoshihito",
    "display_name": "Papa",
    "source": "Nikko for One",
    "snapshot_at": "2026-05-01T16:04:46.675214",
    "valuation": 5583291,
    "profit_loss": null,
    "profit_loss_rate": null,
    "acquisition_cost": null
  },
  {
    "username": "yoshihito",
    "display_name": "Papa",
    "source": "SBI 401K",
    "snapshot_at": "2026-05-01T16:08:10.872216",
    "valuation": 10202458,
    "profit_loss": null,
    "profit_loss_rate": null,
    "acquisition_cost": null
  },
  {
    "username": "yoshihito",
    "display_name": "Papa",
    "source": "SBI証券",
    "snapshot_at": "2026-05-01T16:00:15.143104",
    "valuation": 214788836,
    "profit_loss": 57434881,
    "profit_loss_rate": 38.43,
    "acquisition_cost": 149415024
  },
  {
    "username": "yoshihito",
    "display_name": "Papa",
    "source": "SMBC日興証券",
    "snapshot_at": "2026-05-01T16:03:32.860169",
    "valuation": 5717228,
    "profit_loss": null,
    "profit_loss_rate": null,
    "acquisition_cost": null
  },
  {
    "username": "yoshihito",
    "display_name": "Papa",
    "source": "bitFlyer",
    "snapshot_at": "2026-05-01T16:09:25.348473",
    "valuation": 2300584,
    "profit_loss": null,
    "profit_loss_rate": null,
    "acquisition_cost": null
  },
  {
    "username": "yoshihito",
    "display_name": "Papa",
    "source": "eスマート証券",
    "snapshot_at": "2026-05-01T16:04:02.206907",
    "valuation": 2910003,
    "profit_loss": null,
    "profit_loss_rate": null,
    "acquisition_cost": null
  },
  {
    "username": "yoshihito",
    "display_name": "Papa",
    "source": "みずほDC",
    "snapshot_at": "2026-05-01T16:08:22.276265",
    "valuation": 1517967,
    "profit_loss": 307967,
    "profit_loss_rate": null,
    "acquisition_cost": null
  },
  {
    "username": "yoshihito",
    "display_name": "Papa",
    "source": "みずほ銀行",
    "snapshot_at": "2026-05-01T16:03:23.598453",
    "valuation": 1293148,
    "profit_loss": null,
    "profit_loss_rate": null,
    "acquisition_cost": null
  },
  {
    "username": "yoshihito",
    "display_name": "Papa",
    "source": "楽天銀行",
    "snapshot_at": "2026-04-30T16:06:36.165501",
    "valuation": 515777,
    "profit_loss": null,
    "profit_loss_rate": null,
    "acquisition_cost": null
  },
  {
    "username": "yoshihito",
    "display_name": "Papa",
    "source": "楽天証券",
    "snapshot_at": "2026-04-27T09:25:52.224877",
    "valuation": 5111597,
    "profit_loss": null,
    "profit_loss_rate": null,
    "acquisition_cost": null
  },
  {
    "username": "yoshihito",
    "display_name": "Papa",
    "source": "三井住友銀行",
    "snapshot_at": "2026-05-01T16:08:22.693754",
    "valuation": 398171,
    "profit_loss": null,
    "profit_loss_rate": null,
    "acquisition_cost": null
  },
  {
    "username": "yoshihito",
    "display_name": "Papa",
    "source": "三菱UFJ銀行",
    "snapshot_at": "2026-04-13T16:03:23.107752",
    "valuation": 101178,
    "profit_loss": null,
    "profit_loss_rate": null,
    "acquisition_cost": null
  },
  {
    "username": "yoshihito",
    "display_name": "Papa",
    "source": "三菱UFJ銀行",
    "snapshot_at": "2026-05-01T16:02:55.215969",
    "valuation": 4616218,
    "profit_loss": null,
    "profit_loss_rate": null,
    "acquisition_cost": null
  },
  {
    "username": "yoshihito",
    "display_name": "Papa",
    "source": "三菱UFJ銀行（中目黒支店）",
    "snapshot_at": "2026-04-29T23:33:53.257979",
    "valuation": 101178,
    "profit_loss": null,
    "profit_loss_rate": null,
    "acquisition_cost": null
  },
  {
    "username": "yoshihito",
    "display_name": "Papa",
    "source": "住信SBIネット銀行",
    "snapshot_at": "2026-05-01T16:07:30.927535",
    "valuation": 2161833,
    "profit_loss": null,
    "profit_loss_rate": null,
    "acquisition_cost": null
  },
  {
    "username": "yoshiyukiisogai",
    "display_name": "Brother",
    "source": "SBI証券",
    "snapshot_at": "2026-05-01T16:01:45.455196",
    "valuation": 13022260,
    "profit_loss": 4936749,
    "profit_loss_rate": 61.05,
    "acquisition_cost": 8085511
  },
  {
    "username": "yoshiyukiisogai",
    "display_name": "Brother",
    "source": "三菱UFJ銀行",
    "snapshot_at": "2026-05-01T16:03:21.101364",
    "valuation": 1139922,
    "profit_loss": null,
    "profit_loss_rate": null,
    "acquisition_cost": null
  }
]