{
  "grand_total": 385138068.0,
  "as_of": "2026-04-15T14:55:01.614462",
  "users": [
    {
      "username": "yoshihito",
      "display_name": "Papa",
      "total_valuation": 250236496.0,
      "latest_snapshot": "2026-04-15T13:05:01.635166"
    },
    {
      "username": "masakoisogai",
      "display_name": "Mama",
      "total_valuation": 106129986.0,
      "latest_snapshot": "2026-04-15T13:01:20.607409"
    },
    {
      "username": "nanaisogai",
      "display_name": "Sister",
      "total_valuation": 14568470.0,
      "latest_snapshot": "2026-04-15T13:03:04.786924"
    },
    {
      "username": "yoshiyukiisogai",
      "display_name": "Brother",
      "total_valuation": 14203116.0,
      "latest_snapshot": "2026-04-15T13:02:12.151562"
    }
  ],
  "updated_at": "2026-04-15T14:55:01.761720"
}