{
  "grand_total": 387281696.0,
  "as_of": "2026-04-16T16:05:01.680053",
  "users": [
    {
      "username": "yoshihito",
      "display_name": "Papa",
      "total_valuation": 251878798.0,
      "latest_snapshot": "2026-04-16T16:04:33.907429"
    },
    {
      "username": "masakoisogai",
      "display_name": "Mama",
      "total_valuation": 107083534.0,
      "latest_snapshot": "2026-04-16T16:01:06.791907"
    },
    {
      "username": "yoshiyukiisogai",
      "display_name": "Brother",
      "total_valuation": 14277281.0,
      "latest_snapshot": "2026-04-16T16:03:09.348227"
    },
    {
      "username": "nanaisogai",
      "display_name": "Sister",
      "total_valuation": 14042083.0,
      "latest_snapshot": "2026-04-16T16:03:10.710316"
    }
  ],
  "updated_at": "2026-04-16T16:05:01.846666"
}