[
  {
    "username": "masakoisogai",
    "source": "SBI証券",
    "snapshot_at": "2026-07-06T01:12:44.117856",
    "account_category": "特定預り",
    "asset_type": "stock",
    "asset_class": "国内ETF",
    "ticker_code": "1306",
    "asset_name": "ＮＦＴＯＰＩＸ",
    "quantity": 87300,
    "current_price": 431.7,
    "acquisition_price": 244.0,
    "valuation": 37687410,
    "profit_loss": 16386210,
    "profit_loss_pct": 76.93
  },
  {
    "username": "masakoisogai",
    "source": "SBI証券",
    "snapshot_at": "2026-07-06T01:12:44.117856",
    "account_category": "特定預り",
    "asset_type": "stock",
    "asset_class": "国内ETF",
    "ticker_code": "1658",
    "asset_name": "ｉＳＭＳＣＩ新興国株",
    "quantity": 3713,
    "current_price": 4531.0,
    "acquisition_price": 2274.0,
    "valuation": 16823603,
    "profit_loss": 8380241,
    "profit_loss_pct": 99.25
  },
  {
    "username": "masakoisogai",
    "source": "SBI証券",
    "snapshot_at": "2026-07-06T01:12:44.117856",
    "account_category": "特定預り",
    "asset_type": "stock",
    "asset_class": "国内ETF",
    "ticker_code": "1657",
    "asset_name": "ｉＳＭＳＣＩ先進国株",
    "quantity": 1377,
    "current_price": 7280.0,
    "acquisition_price": 3793.0,
    "valuation": 10024560,
    "profit_loss": 4801599,
    "profit_loss_pct": 91.93
  },
  {
    "username": "masakoisogai",
    "source": "SBI証券",
    "snapshot_at": "2026-07-06T01:12:44.117856",
    "account_category": "特定預り",
    "asset_type": "stock",
    "asset_class": "国内ETF",
    "ticker_code": "2559",
    "asset_name": "ＭＸＳ全世界株式",
    "quantity": 2880,
    "current_price": 2982.0,
    "acquisition_price": 1932.0,
    "valuation": 8588160,
    "profit_loss": 3024000,
    "profit_loss_pct": 54.35
  },
  {
    "username": "masakoisogai",
    "source": "SBI証券",
    "snapshot_at": "2026-07-06T01:12:44.117856",
    "account_category": "特定預り",
    "asset_type": "stock",
    "asset_class": "国内株式",
    "ticker_code": "1563",
    "asset_name": "東証グロース・コア",
    "quantity": 3000,
    "current_price": 2312.0,
    "acquisition_price": 2030.0,
    "valuation": 6936000,
    "profit_loss": 846000,
    "profit_loss_pct": 13.89
  },
  {
    "username": "masakoisogai",
    "source": "SBI証券",
    "snapshot_at": "2026-07-06T01:12:44.117856",
    "account_category": "NISA預り（つみたて投資枠）",
    "asset_type": "fund",
    "asset_class": "投資信託",
    "ticker_code": null,
    "asset_name": "ｅＭＡＸＩＳ　Ｓｌｉｍ　全世界株式（オール・カントリー）",
    "quantity": 1115329,
    "current_price": 38009.0,
    "acquisition_price": 27418.0,
    "valuation": 4239253,
    "profit_loss": 1181244,
    "profit_loss_pct": null
  },
  {
    "username": "masakoisogai",
    "source": "SBI証券",
    "snapshot_at": "2026-07-06T01:12:44.117856",
    "account_category": "NISA預り（成長投資枠）",
    "asset_type": "stock",
    "asset_class": "国内ETF",
    "ticker_code": "1306",
    "asset_name": "ＮＦＴＯＰＩＸ",
    "quantity": 9000,
    "current_price": 431.7,
    "acquisition_price": 288.0,
    "valuation": 3885300,
    "profit_loss": 1293300,
    "profit_loss_pct": 49.9
  },
  {
    "username": "masakoisogai",
    "source": "SBI証券",
    "snapshot_at": "2026-07-06T01:12:44.117856",
    "account_category": "旧NISA預り",
    "asset_type": "stock",
    "asset_class": "国内ETF",
    "ticker_code": "2559",
    "asset_name": "ＭＸＳ全世界株式",
    "quantity": 760,
    "current_price": 2982.0,
    "acquisition_price": 1563.0,
    "valuation": 2266320,
    "profit_loss": 1078440,
    "profit_loss_pct": 90.79
  },
  {
    "username": "masakoisogai",
    "source": "SBI証券",
    "snapshot_at": "2026-07-06T01:12:44.117856",
    "account_category": "旧NISA預り",
    "asset_type": "stock",
    "asset_class": "国内ETF",
    "ticker_code": "1680",
    "asset_name": "上場ＭＳコク",
    "quantity": 170,
    "current_price": 8313.0,
    "acquisition_price": 2029.0,
    "valuation": 1413210,
    "profit_loss": 1068280,
    "profit_loss_pct": 309.71
  },
  {
    "username": "masakoisogai",
    "source": "SBI証券",
    "snapshot_at": "2026-07-06T01:12:44.117856",
    "account_category": "旧NISA預り",
    "asset_type": "stock",
    "asset_class": "国内ETF",
    "ticker_code": "1306",
    "asset_name": "ＮＦＴＯＰＩＸ",
    "quantity": 3000,
    "current_price": 431.7,
    "acquisition_price": 172.0,
    "valuation": 1295100,
    "profit_loss": 779100,
    "profit_loss_pct": 150.99
  },
  {
    "username": "masakoisogai",
    "source": "SBI証券",
    "snapshot_at": "2026-07-06T01:12:44.117856",
    "account_category": "NISA預り（成長投資枠）",
    "asset_type": "fund",
    "asset_class": "投資信託",
    "ticker_code": null,
    "asset_name": "ｅＭＡＸＩＳ　Ｓｌｉｍ　全世界株式（オール・カントリー）",
    "quantity": 189664,
    "current_price": 38009.0,
    "acquisition_price": 37170.0,
    "valuation": 720893,
    "profit_loss": 15912,
    "profit_loss_pct": null
  },
  {
    "username": "masakoisogai",
    "source": "SBI証券",
    "snapshot_at": "2026-07-06T01:12:44.117856",
    "account_category": "特定預り",
    "asset_type": "stock",
    "asset_class": "国内株式",
    "ticker_code": "9202",
    "asset_name": "ＡＮＡ",
    "quantity": 200,
    "current_price": 3140.0,
    "acquisition_price": 2207.0,
    "valuation": 628000,
    "profit_loss": 186600,
    "profit_loss_pct": 42.27
  },
  {
    "username": "masakoisogai",
    "source": "SBI証券",
    "snapshot_at": "2026-07-06T01:12:44.117856",
    "account_category": "特定預り",
    "asset_type": "stock",
    "asset_class": "国内ETF",
    "ticker_code": "1681",
    "asset_name": "上場ＭＳエマ",
    "quantity": 160,
    "current_price": 3456.0,
    "acquisition_price": 2783.0,
    "valuation": 552960,
    "profit_loss": 107680,
    "profit_loss_pct": 24.18
  },
  {
    "username": "masakoisogai",
    "source": "SBI証券",
    "snapshot_at": "2026-07-06T01:12:44.117856",
    "account_category": "特定預り",
    "asset_type": "stock",
    "asset_class": "国内株式",
    "ticker_code": "3197",
    "asset_name": "すかいらーくＨＤ",
    "quantity": 100,
    "current_price": 2849.0,
    "acquisition_price": 1529.0,
    "valuation": 284900,
    "profit_loss": 132000,
    "profit_loss_pct": 86.33
  },
  {
    "username": "masakoisogai",
    "source": "SBI証券",
    "snapshot_at": "2026-07-06T01:12:44.117856",
    "account_category": "特定預り",
    "asset_type": "stock",
    "asset_class": "国内株式",
    "ticker_code": "3067",
    "asset_name": "東京一番フーズ",
    "quantity": 500,
    "current_price": 453.0,
    "acquisition_price": 450.0,
    "valuation": 226500,
    "profit_loss": 1500,
    "profit_loss_pct": 0.67
  },
  {
    "username": "masakoisogai",
    "source": "SBI証券",
    "snapshot_at": "2026-07-06T01:12:44.117856",
    "account_category": "NISA預り（成長投資枠）",
    "asset_type": "stock",
    "asset_class": "国内ETF",
    "ticker_code": "1657",
    "asset_name": "ｉＳＭＳＣＩ先進国株",
    "quantity": 30,
    "current_price": 7280.0,
    "acquisition_price": 5115.0,
    "valuation": 218400,
    "profit_loss": 64950,
    "profit_loss_pct": 42.33
  },
  {
    "username": "masakoisogai",
    "source": "SBI証券",
    "snapshot_at": "2026-07-06T01:12:44.117856",
    "account_category": "NISA預り（成長投資枠）",
    "asset_type": "stock",
    "asset_class": "国内ETF",
    "ticker_code": "2559",
    "asset_name": "ＭＸＳ全世界株式",
    "quantity": 70,
    "current_price": 2982.0,
    "acquisition_price": 1933.0,
    "valuation": 208740,
    "profit_loss": 73430,
    "profit_loss_pct": 54.27
  },
  {
    "username": "masakoisogai",
    "source": "SBI証券",
    "snapshot_at": "2026-07-06T01:12:44.117856",
    "account_category": "NISA預り（成長投資枠）",
    "asset_type": "fund",
    "asset_class": "投資信託",
    "ticker_code": null,
    "asset_name": "ｅＭＡＸＩＳ　Ｓｌｉｍ　先進国株式インデックス（除く日本）",
    "quantity": 22357,
    "current_price": 45220.0,
    "acquisition_price": 44074.0,
    "valuation": 101098,
    "profit_loss": 2562,
    "profit_loss_pct": null
  },
  {
    "username": "masakoisogai",
    "source": "SBI証券",
    "snapshot_at": "2026-07-06T01:12:44.117856",
    "account_category": "特定預り",
    "asset_type": "stock",
    "asset_class": "国内株式",
    "ticker_code": "4755",
    "asset_name": "楽天グループ",
    "quantity": 100,
    "current_price": 764.0,
    "acquisition_price": 866.0,
    "valuation": 76400,
    "profit_loss": -10200,
    "profit_loss_pct": -11.78
  },
  {
    "username": "masakoisogai",
    "source": "SBI証券",
    "snapshot_at": "2026-07-06T01:12:44.117856",
    "account_category": "旧NISA預り",
    "asset_type": "fund",
    "asset_class": "投資信託",
    "ticker_code": null,
    "asset_name": "ｅＭＡＸＩＳ　ＴＯＰＩＸインデックス",
    "quantity": 9213,
    "current_price": 61496.0,
    "acquisition_price": 27331.0,
    "valuation": 56656,
    "profit_loss": 31476,
    "profit_loss_pct": null
  },
  {
    "username": "masakoisogai",
    "source": "SBI証券",
    "snapshot_at": "2026-07-06T01:12:44.117856",
    "account_category": "特定預り",
    "asset_type": "fund",
    "asset_class": "投資信託",
    "ticker_code": null,
    "asset_name": "ｅＭＡＸＩＳ　Ｓｌｉｍ　国内債券インデックス",
    "quantity": 37406,
    "current_price": 8490.0,
    "acquisition_price": 8500.0,
    "valuation": 31757,
    "profit_loss": -38,
    "profit_loss_pct": null
  },
  {
    "username": "masakoisogai",
    "source": "SBI証券",
    "snapshot_at": "2026-07-06T01:12:44.117856",
    "account_category": "特定預り",
    "asset_type": "fund",
    "asset_class": "投資信託",
    "ticker_code": null,
    "asset_name": "ＳＢＩ・Ｖ・Ｓ＆Ｐ５００インデックス・ファンド",
    "quantity": 6374,
    "current_price": 40501.0,
    "acquisition_price": 31278.0,
    "valuation": 25815,
    "profit_loss": 5879,
    "profit_loss_pct": null
  },
  {
    "username": "masakoisogai",
    "source": "SBI証券",
    "snapshot_at": "2026-07-06T01:12:44.117856",
    "account_category": "NISA預り（成長投資枠）",
    "asset_type": "stock",
    "asset_class": "国内ETF",
    "ticker_code": "1658",
    "asset_name": "ｉＳＭＳＣＩ新興国株",
    "quantity": 5,
    "current_price": 4531.0,
    "acquisition_price": 2410.0,
    "valuation": 22655,
    "profit_loss": 10605,
    "profit_loss_pct": 88.01
  },
  {
    "username": "masakoisogai",
    "source": "SBI証券",
    "snapshot_at": "2026-07-06T01:12:44.117856",
    "account_category": "特定預り",
    "asset_type": "stock",
    "asset_class": "国内株式",
    "ticker_code": "9432",
    "asset_name": "ＮＴＴ",
    "quantity": 100,
    "current_price": 146.1,
    "acquisition_price": 150.0,
    "valuation": 14610,
    "profit_loss": -390,
    "profit_loss_pct": -2.6
  },
  {
    "username": "masakoisogai",
    "source": "SBI証券",
    "snapshot_at": "2026-07-06T01:12:44.117856",
    "account_category": "NISA預り（成長投資枠）",
    "asset_type": "fund",
    "asset_class": "投資信託",
    "ticker_code": null,
    "asset_name": "ｅＭＡＸＩＳ　Ｓｌｉｍ　新興国株式インデックス",
    "quantity": 2561,
    "current_price": 27429.0,
    "acquisition_price": 26998.0,
    "valuation": 7024,
    "profit_loss": 110,
    "profit_loss_pct": null
  },
  {
    "username": "masakoisogai",
    "source": "SBI証券",
    "snapshot_at": "2026-07-06T01:12:44.117856",
    "account_category": "DOMESTIC_DEPOSIT",
    "asset_type": null,
    "asset_class": "国内預金",
    "ticker_code": null,
    "asset_name": "現金・預り金",
    "quantity": null,
    "current_price": null,
    "acquisition_price": null,
    "valuation": -3997,
    "profit_loss": null,
    "profit_loss_pct": null
  }
]